dsalgo/__init__.py
dsalgo/boruvka.py
dsalgo/connected_components.py
dsalgo/connected_components_bfs.py
dsalgo/connected_components_dfs.py
dsalgo/connected_components_uf.py
dsalgo/cp/__init__.py
dsalgo/debug.py
dsalgo/disjoint_set_union.py
dsalgo/dsu.py
dsalgo/kruskal_uf.py
dsalgo/len_proto.py
dsalgo/minimum_spanning_tree.py
dsalgo/mst.py
dsalgo/mst_rondomized_linear.py
dsalgo/nb/__init__.py
dsalgo/np/__init__.py
dsalgo/option.py
dsalgo/prim_dense.py
dsalgo/prim_sparse.py
dsalgo/result.py
dsalgo/reverse_delete.py
dsalgo/scc.py
dsalgo/scc_kosaraju.py
dsalgo/scc_path_based.py
dsalgo/scc_tarjan_lowlink.py
dsalgo/strongly_connected_components.py
dsalgo/trigonometly.py
dsalgo/union_find.py
dsalgo/union_find_by_rank.py
dsalgo/union_find_by_size.py
dsalgo/union_find_labels.py
dsalgo/union_find_optimized.py
dsalgo/union_find_path_compression.py
dsalgo/union_find_proto.py
dsalgo-0.3.7.dist-info/METADATA
dsalgo-0.3.7.dist-info/LICENSE
dsalgo-0.3.7.dist-info/WHEEL
dsalgo-0.3.7.dist-info/RECORD
