Metadata-Version: 2.1
Name: dsalgo
Version: 0.3.7
Summary: A package for datastructures and algorithms.
Home-page: https://github.com/kagemeka/dsalgo-python#readme
License: MIT
Keywords: algorithm,datastructure
Author: kagemeka
Author-email: kagemeka1@gmail.com
Requires-Python: >=3.10,<4.0
Classifier: License :: OSI Approved :: MIT License
Classifier: Programming Language :: Python :: 3
Classifier: Programming Language :: Python :: 3.10
Classifier: Programming Language :: Python :: 3.11
Provides-Extra: nb
Requires-Dist: numba (>=0.56,<0.57) ; (python_version < "3.11") and (extra == "nb")
Requires-Dist: numpy
Requires-Dist: scipy
Project-URL: Documentation, https://kagemeka.github.io/dsalgo-python
Project-URL: Repository, https://github.com/kagemeka/dsalgo-python
